LICENSE
pose_classification_kit/__init__.py
pose_classification_kit/app.py
pose_classification_kit/config.py
pose_classification_kit/datasets/__init__.py
pose_classification_kit/datasets/Body/MilitarySalute_body.json
pose_classification_kit/datasets/Body/Plank_body.json
pose_classification_kit/datasets/Body/PushUp_Low_body.json
pose_classification_kit/datasets/Body/Seated_body.json
pose_classification_kit/datasets/Body/Squat_body.json
pose_classification_kit/datasets/Body/Stand_body.json
pose_classification_kit/datasets/Body/Stand_LeftArmRaised_body.json
pose_classification_kit/datasets/Body/Stand_RightArmRaised_body.json
pose_classification_kit/datasets/Body/T_body.json
pose_classification_kit/datasets/Body/Traffic_AllStop_body.json
pose_classification_kit/datasets/Body/Traffic_BackFrontStop_body.json
pose_classification_kit/datasets/Body/Traffic_BackStop_body.json
pose_classification_kit/datasets/Body/Traffic_FrontStop_body.json
pose_classification_kit/datasets/Body/Traffic_LeftTurn_body.json
pose_classification_kit/datasets/Body/Traffic_RightTurn_body.json
pose_classification_kit/datasets/Body/Yoga_Tree_left_body.json
pose_classification_kit/datasets/Body/Yoga_Tree_right_body.json
pose_classification_kit/datasets/Body/Yoga_UpwardSalute_body.json
pose_classification_kit/datasets/Body/Yoga_Warrior2_left_body.json
pose_classification_kit/datasets/Body/Yoga_Warrior2_right_body.json
pose_classification_kit/datasets/body_models.py
pose_classification_kit/datasets/BodyPose_Dataset.csv
pose_classification_kit/datasets/data_augmentation.py
pose_classification_kit/datasets/HandPose_Dataset.csv
pose_classification_kit/datasets/Hands/0_left_hand.json
pose_classification_kit/datasets/Hands/0_right_hand.json
pose_classification_kit/datasets/Hands/1_left_hand.json
pose_classification_kit/datasets/Hands/1_right_hand.json
pose_classification_kit/datasets/Hands/2_left_hand.json
pose_classification_kit/datasets/Hands/2_right_hand.json
pose_classification_kit-1.1.5.dist-info/entry_points.txt
pose_classification_kit-1.1.5.dist-info/LICENSE
pose_classification_kit-1.1.5.dist-info/WHEEL
pose_classification_kit-1.1.5.dist-info/METADATA
pose_classification_kit-1.1.5.dist-info/RECORD
