Metadata-Version: 2.1
Name: pose-classification-kit
Version: 1.1.5
Summary: From pose estimation to pose classification - Creation of datasets & real-time visualization
Home-page: https://github.com/ArthurFDLR/pose-classification-kit
License: MIT
Keywords: pose-classification,OpenPose,pose-estimation,machine-learning,deep-learning,keypoints,keypoints-detection,gesture
Author: ArthurFDLR
Author-email: arthfind@gmail.com
Requires-Python: >=3.6.2,<4.0
Classifier: Development Status :: 5 - Production/Stable
Classifier: Environment :: X11 Applications :: Qt
Classifier: Intended Audience :: End Users/Desktop
Classifier: Intended Audience :: Science/Research
Classifier: License :: OSI Approved :: MIT License
Classifier: Programming Language :: Python :: 3
Classifier: Programming Language :: Python :: 3 :: Only
Classifier: Programming Language :: Python :: 3.6
Classifier: Programming Language :: Python :: 3.7
Classifier: Programming Language :: Python :: 3.8
Classifier: Programming Language :: Python :: 3.9
Classifier: Topic :: Scientific/Engineering :: Artificial Intelligence
Classifier: Topic :: Scientific/Engineering :: Image Recognition
Provides-Extra: app
Requires-Dist: PyQt5 (>=5.15.4,<6.0.0); extra == "app"
Requires-Dist: matplotlib (>=3.3.2,<4.0.0); extra == "app"
Requires-Dist: numpy (>=1.19.2,<1.20.0)
Requires-Dist: opencv-python (>=4.4.0,<5.0.0); extra == "app"
Requires-Dist: pandas (>=1.1.5,<2.0.0)
Requires-Dist: qimage2ndarray (>=1.8.3,<2.0.0); extra == "app"
Requires-Dist: tensorflow
Project-URL: Repository, https://github.com/ArthurFDLR/pose-classification-kit
